{
  "koalas": [
    {
      "id": "k001",
      "name": "茉莉",
      "birthDate": "2015-03",
      "sex": "female",
      "photo": "/images/koalas/moli.jpg",
      "mother": null,
      "father": null,
      "deceased": true,
      "dateOfDeath": "2025-01-14",
      "tags": [
        "茉莉妈妈",
        "茉莉女士",
        "Merindah"
      ]
    },
    {
      "id": "k002",
      "name": "梧桐",
      "birthDate": "2014-11",
      "sex": "male",
      "photo": "/images/koalas/wutong.jpg",
      "mother": null,
      "father": null,
      "tags": [
        "梧桐爸爸",
        "Pinpen"
      ]
    },
    {
      "id": "k003",
      "name": "柠檬",
      "birthDate": "2018-02",
      "sex": "female",
      "photo": "/images/koalas/ningmeng.jpg",
      "mother": "k001",
      "father": "k002",
      "tags": [
        "柠檬公主",
        "11",
        "Matilda"
      ]
    },
    {
      "id": "k004",
      "name": "柚子",
      "birthDate": "2019-02-24",
      "sex": "male",
      "photo": "/images/koalas/youzi.jpg",
      "mother": "k001",
      "father": "k002",
      "deceased": true,
      "dateOfDeath": "2023-06-08",
      "tags": [
        "Banjo"
      ]
    },
    {
      "id": "k005",
      "name": "金桔",
      "birthDate": "2020-06-17",
      "sex": "female",
      "photo": "/images/koalas/jinju.jpg",
      "mother": "k001",
      "father": "k002",
      "deceased": true,
      "dateOfDeath": "2024-02-28",
      "tags": [
        "Opal"
      ]
    },
    {
      "id": "k006",
      "name": "橙子",
      "birthDate": "2021-11-06",
      "sex": "male",
      "photo": "/images/koalas/chengzi.jpg",
      "mother": "k001",
      "father": "k002",
      "tags": [
        "Jarrah"
      ]
    },
    {
      "id": "k007",
      "name": "青柑",
      "birthDate": "2022-12-14",
      "sex": "female",
      "photo": "/images/koalas/qinggan.jpg",
      "mother": "k001",
      "father": "k002",
      "tags": [
        "五宝",
        "55",
        "Kirra"
      ]
    },
    {
      "id": "k008",
      "name": "青柠",
      "birthDate": "2024-05-04",
      "sex": "female",
      "photo": "/images/koalas/liubao.jpg",
      "mother": "k001",
      "father": "k002",
      "tags": [
        "六宝",
        "66"
      ]
    }
  ]
}
